{
	"#centering": "t",
	"#logo": "n",
	".mail_b": "r",
	".read_us": "i",
	"#vk": "s",
	"#twitt": "o",
	"#social_label": "u",
	".login_td": "a",
	".top_link_login_authorized": "f",
	".top_link_login": "l",
	".ya-site-form__input": "c",
	".ya-site-form__input-text": "h",
	"#Buscar": "p",
	"#content": "d",
	"#patch": "v",
	"#nav": "m",
	"#m_m_left_item": "g",
	"#m_m_right_item": "y",
	"#home": "b",
	"#Art": "w",
	"#Noticias": "x",
	"#Video": "k",
	"#Presen": "_",
	"#Pruebas": "j",
	"#Enfermedades": "q",
	"#Farmacia": "z",
	"#Calculadoras": "te",
	"#Foro": "tt",
	"#main": "tn",
	".startdate": "tr",
	".holder": "ti",
	".pic": "ts",
	".title": "to",
	".date": "tu",
	".ord_button": "ta",
	"#tab1_span": "tf",
	"#aside": "tl",
	".div_3col": "tc",
	"#aside_bot_bold_ul": "th",
	".CollapsiblePanelContent": "tp",
	".description_text": "td",
	".box": "tv"
}